paytring/__init__.py
paytring/client.py
paytring/constant/__init__.py
paytring/constant/url.py
paytring/resources/__init__.py
paytring/resources/paytring.py
paytring/utility/__init__.py
paytring/utility/utility.py
paytring-1.0.7.dist-info/LICENSE.txt
paytring-1.0.7.dist-info/METADATA
paytring-1.0.7.dist-info/WHEEL
paytring-1.0.7.dist-info/top_level.txt
paytring-1.0.7.dist-info/RECORD
