Metadata-Version: 2.1
Name: paytring
Version: 1.0.7
Summary: A SDK which helps to create, fetch or refund an order on Paytring
Home-page: https://github.com/paytring/python-sdk
Author: Paytirng
Author-email: developer@paytring.com
License: MIT
Classifier: License :: OSI Approved :: MIT License
Classifier: Programming Language :: Python :: 3.10
Classifier: Operating System :: OS Independent
Requires-Python: >=3.10
License-File: LICENSE.txt
Requires-Dist: requests (==2.31.0)
Requires-Dist: urllib3 (==2.0.2)
